h5netcdf/__init__.py
h5netcdf/_version.py
h5netcdf/attrs.py
h5netcdf/core.py
h5netcdf/dimensions.py
h5netcdf/legacyapi.py
h5netcdf/utils.py
h5netcdf/tests/conftest.py
h5netcdf/tests/pytest.ini
h5netcdf/tests/test_h5netcdf.py
h5netcdf-1.7.2.dist-info/licenses/AUTHORS.txt
h5netcdf-1.7.2.dist-info/licenses/LICENSE
h5netcdf-1.7.2.dist-info/METADATA
h5netcdf-1.7.2.dist-info/WHEEL
h5netcdf-1.7.2.dist-info/top_level.txt
h5netcdf-1.7.2.dist-info/RECORD
