Metadata-Version: 2.4
Name: h5netcdf
Version: 1.7.2
Summary: netCDF4 via h5py
Author-email: Stephan Hoyer <shoyer@gmail.com>, Kai Mühlbauer <kmuehlbauer@wradlib.org>
Maintainer-email: h5netcdf developers <devteam@h5netcdf.org>
License: Copyright (c) 2015, h5netcdf developers
Project-URL: homepage, https://h5netcdf.org
Project-URL: documentation, https://h5netcdf.org
Project-URL: repository, https://github.com/h5netcdf/h5netcdf
Project-URL: changelog, https://github.com/h5netcdf/h5netcdf/blob/main/CHANGELOG.rst
Classifier: Development Status :: 5 - Production/Stable
Classifier: License :: OSI Approved :: BSD License
Classifier: Operating System :: OS Independent
Classifier: Intended Audience :: Science/Research
Classifier: Programming Language :: Python
Classifier: Programming Language :: Python :: 3
Classifier: Programming Language :: Python :: 3.9
Classifier: Programming Language :: Python :: 3.10
Classifier: Programming Language :: Python :: 3.11
Classifier: Programming Language :: Python :: 3.12
Classifier: Topic :: Scientific/Engineering
Requires-Python: >=3.9
License-File: LICENSE
License-File: AUTHORS.txt
Requires-Dist: h5py
Requires-Dist: packaging
Provides-Extra: test
Requires-Dist: netCDF4; extra == "test"
Requires-Dist: pytest; extra == "test"
Dynamic: license-file
